data_logger_sdk/__init__.py
data_logger_sdk/constants.py
data_logger_sdk/dag.yml
data_logger_sdk/data_logger_sdk.py
data_logger_sdk/data_logger_sdk_config.py
data_logger_sdk/lib.py
data_logger_sdk/py.typed
data_logger_sdk/runtime_conf.py
data_logger_sdk/self_logging.py
data_logger_sdk/brokers/__init__.py
data_logger_sdk/brokers/data_logger_input_broker.py
data_logger_sdk/messages/__init__.py
data_logger_sdk/messages/bs_data_logger_input_message.py
data_logger_sdk/messages/http_nero_bs_packet_input_message.py
data_logger_sdk/messages/universal_api_data_logger_input_message.py
ul_data_logger_sdk-3.0.4.dist-info/METADATA
ul_data_logger_sdk-3.0.4.dist-info/WHEEL
ul_data_logger_sdk-3.0.4.dist-info/top_level.txt
ul_data_logger_sdk-3.0.4.dist-info/RECORD
